{
  "data": {
    "meta": {
      "adoptsFrom": {
        "name": "CalendarEvent",
        "module": "../calendar"
      }
    },
    "type": "card",
    "attributes": {
      "cardTitle": "Algebra 1",
      "endTime": "2025-09-11T02:00:00.000Z",
      "cardInfo": {
        "notes": null,
        "name": null,
        "summary": null,
        "cardThumbnailURL": null
      },
      "isAllDay": "false",
      "location": null,
      "eventType": "meeting",
      "startTime": "2025-09-11T01:00:00.000Z",
      "eventColor": null,
      "cardDescription": null
    },
    "relationships": {
      "calendar": {
        "links": {
          "self": "../CalendarCard/2c3c78cd-fa4f-4988-b098-c8d099557fba"
        }
      },
      "cardInfo.theme": {
        "links": {
          "self": null
        }
      }
    }
  }
}
