{
  "data": {
    "meta": {
      "adoptsFrom": {
        "name": "PolaroidImage",
        "module": "../time-machine/polaroid-image"
      }
    },
    "type": "card",
    "attributes": {
      "image": {},
      "caption": "2000s",
      "cardInfo": {
        "notes": null,
        "title": null,
        "description": null,
        "thumbnailURL": null
      }
    },
    "relationships": {
      "cardInfo.theme": {
        "links": {
          "self": null
        }
      },
      "image.imageCard": {
        "links": {
          "self": "../CloudflareImage/e0272271-efb1-4218-85ba-bef85fc9b81c"
        }
      }
    }
  }
}