{
  "data": {
    "type": "card",
    "attributes": {
      "name": "Card",
      "color": "#10B981",
      "cardInfo": {
        "notes": null,
        "name": "Card",
        "summary": "Simple single-purpose cards that display or capture one focused piece of information.",
        "cardThumbnailURL": null
      }
    },
    "meta": {
      "adoptsFrom": {
        "module": "../catalog-app/listing/tag",
        "name": "Tag"
      }
    },
    "relationships": {
      "cardInfo.theme": {
        "links": {
          "self": null
        }
      }
    }
  }
}
