{
  "data": {
    "type": "card",
    "attributes": {
      "title": "Chain from /chain",
      "description": "Catalog entry for Chain from /chain",
      "ref": {
        "module": "../chain",
        "name": "Chain"
      },
      "demo": {
        "name": "Ethereum Mainnet"
      }
    },
    "meta": {
      "fields": {
        "demo": {
          "adoptsFrom": {
            "module": "../chain",
            "name": "Chain"
          }
        }
      },
      "adoptsFrom": {
        "module": "https://cardstack.com/base/catalog-entry",
        "name": "CatalogEntry"
      }
    }
  }
}
