{
  "data": {
    "meta": {
      "adoptsFrom": {
        "name": "SkillsSection",
        "module": "../skills-section"
      }
    },
    "type": "card",
    "attributes": {
      "skills": [],
      "bullets": [],
      "cardInfo": {
        "notes": null,
        "title": "Skills",
        "description": null,
        "thumbnailURL": null
      },
      "headline": "Choose your model. Own your prompts.",
      "footerNote": null,
      "subheadline": "Everything the AI does—vibe coding, workspace orchestration, assistant behavior—is powered by skill cards you can inspect, modify, or replace.",
      "sectionLabel": "AI Extensibility",
      "sectionNumber": "005"
    },
    "relationships": {
      "cardInfo.theme": {
        "links": {
          "self": null
        }
      }
    }
  }
}