{
  "data": {
    "type": "card",
    "attributes": {
      "name": "Travel Experiences",
      "description": "Trip planning, destination guides, accommodation booking, travel itineraries, local experiences, and adventure activities.",
      "color": "#0891b2",
      "order": 6
    },
    "relationships": {
      "sphere": {
        "links": {
          "self": "../Sphere/5d7420dc-c8f6-491d-9570-60c01e07b14c"
        }
      }
    },
    "meta": {
      "adoptsFrom": {
        "module": "../catalog-app/listing/category",
        "name": "Category"
      }
    }
  }
}
