{
  "data": {
    "type": "card",
    "attributes": {
      "firstName": "Alice",
      "lastName": "Enwunder",
      "bio": null,
      "fullBio": null,
      "quote": "Curiouser and curiouser",
      "contactLinks": [
        {
          "label": "X",
          "value": "https://x.com/alice-boxel"
        },
        {
          "label": "LinkedIn",
          "value": "https://linkedin.com/alice-boxel"
        },
        {
          "label": "Email",
          "value": "alice@email.com"
        }
      ],
      "email": null,
      "featuredImage": {
        "imageUrl": "https://boxel-images.boxel.ai/app-assets/portraits/photo-1509868918748-a554ad25f858.jpeg",
        "credit": "Photo via Unsplash",
        "caption": null,
        "altText": "Alice Enwunder",
        "size": "actual",
        "height": null,
        "width": null
      },
      "cardInfo": {
        "description": null,
        "thumbnailURL": "https://boxel-images.boxel.ai/app-assets/portraits/photo-1509868918748-a554ad25f858.jpeg"
      }
    },
    "relationships": {
      "blog": {
        "links": {
          "self": null
        }
      }
    },
    "meta": {
      "adoptsFrom": {
        "module": "../author",
        "name": "Author"
      }
    }
  }
}
