{
  "data": {
    "meta": {
      "fields": {
        "containedExamples": [
          {
            "adoptsFrom": {
              "module": "../fields/image/avatar",
              "name": "default"
            }
          }
        ]
      },
      "adoptsFrom": {
        "name": "Spec",
        "module": "https://cardstack.com/base/spec"
      }
    },
    "type": "card",
    "attributes": {
      "ref": {
        "name": "default",
        "module": "../fields/image/avatar"
      },
      "title": "default",
      "readMe": null,
      "cardInfo": {
        "notes": null,
        "title": null,
        "description": null,
        "thumbnailURL": null
      },
      "specType": "field",
      "description": null,
      "containedExamples": [
        {
          "uploadUrl": "https://upload.imagedelivery.net/TB1OM65i5Go9UkT2wcBzeA/upload-1763647749195",
          "uploadedImageUrl": "https://imagedelivery.net/TB1OM65i5Go9UkT2wcBzeA/upload-1763647749195/public"
        }
      ]
    },
    "relationships": {
      "cardInfo.theme": {
        "links": {
          "self": null
        }
      },
      "linkedExamples": {
        "links": {
          "self": null
        }
      }
    }
  }
}