{
  "data": {
    "type": "card",
    "attributes": {
      "readMe": null,
      "ref": {
        "name": "SprintPlanner",
        "module": "../sprint-planner/sprint-planner"
      },
      "specType": "card",
      "containedExamples": [],
      "cardTitle": "SprintPlanner",
      "cardDescription": "Spec of Sprint Planner",
      "cardThumbnailURL": null
    },
    "relationships": {
      "linkedExamples": {
        "links": {
          "self": null
        }
      }
    },
    "meta": {
      "adoptsFrom": {
        "module": "https://cardstack.com/base/spec",
        "name": "Spec"
      }
    }
  }
}
